{"events":[{"date_id":"","date":"","title":"","location":"","description":""},{"date_id":"2016.10.10","date":"10/10/2016","title":"GO HIKING","location":"Mountain Bear","description":"I plan to go hiking with my big brother!"},{"date_id":"2016.10.10","date":"10/10/2016","title":"Go dancing","location":"Central Square","description":"Having  a show for a mall"},{"date_id":"2016.10.19","date":"10/19/2016","title":"Interview with Amazon","location":"Home","description":"Please prepare for it"},{"date_id":"2016.10.22","date":"10/22/2016","title":"singing","location":"flushing","description":"singing with friends"},{"date_id":"2016.10.13","date":"10/13/2016","title":"GO HIKING","location":"Yellow Stone","description":"For fun"},{"date_id":"2016.9.20","date":"09/20/2016","title":"Playing basketball with roommates","location":"Washington Park","description":"Work out"},{"date_id":"2016.11.16","date":"11/16/2016","title":"Mid-term exam","location":"Main building","description":"Math test"},{"date_id":"2016.11.21","date":"11/21/2016 12:00 AM","title":"Go fishing","location":"one special lake","description":"fishing big fishes"},{"date_id":"2016.10.14","date":"10/14/2016","title":"Go fishing","location":"one special lake","description":"fishing big fishes"},{"date_id":"2016.10.13","date":"10/13/2016","title":"Reading","location":"School Library","description":"Reading newspaper"},{"date_id":"2016.10.6","date":"2016-10-06","title":"dancing","location":"school","description":"for fun"},{"date_id":"2016.10.18","date":"2016-10-18","title":"study","location":"library","description":"mid-term exam"},{"date_id":"2016.10.18","date":"2016-10-18","title":"singing","location":"flushing","description":"with friends"},{"date_id":"2016.10.11","date":"2016-10-11","title":"test","location":"school","description":"math"},{"date_id":"2016.10.19","date":"2016-10-19","title":"dance","location":"home","description":"for fun"},{"date_id":"2016.3.17","date":"2016-03-17","title":"doing lunch","location":" at home","description":"for girl friend"},{"date_id":"2016.11.30","date":"2016-11-30","title":"Preparing for the final exam","location":"In the library","description":"study hard"},{"date_id":"2016.12.15","date":"2016-12-15","title":"Go shopping for Christmas Day","location":"Warl-Mat","description":"go to buy some Christmas Tree"},{"date_id":"2016.12.5","date":"2016-12-05","title":"Do some preparation for the coming finals","location":"in the library","description":"work hard"},{"date_id":"2017.1.10","date":"2017-01-10","title":"Make a plan for the coming semester","location":"at home","description":"looking for a job"}]}
